wordpress_api/__init__.py
wordpress_api/feed_views.py
wordpress_api/models.py
wordpress_api/tests.py
wordpress_api/urls.py
wordpress_api/utils.py
wordpress_api/views.py
django_wordpress_api-0.2.0.dist-info/AUTHORS.rst
django_wordpress_api-0.2.0.dist-info/LICENSE
django_wordpress_api-0.2.0.dist-info/METADATA
django_wordpress_api-0.2.0.dist-info/WHEEL
django_wordpress_api-0.2.0.dist-info/top_level.txt
django_wordpress_api-0.2.0.dist-info/RECORD
