Metadata-Version: 2.1
Name: django-wordpress-api
Version: 0.2.0
Summary: Easily Install your Wordpress blog in your Django project using wp rest API v1
Home-page: https://github.com/swappsco/django-wordpress-api
Author: Swapps
Author-email: dev@swapps.io
License: MIT
Keywords: django-wordpress-api
Platform: UNKNOWN
Classifier: Development Status :: 3 - Alpha
Classifier: Framework :: Django
Classifier: Framework :: Django :: 1.11
Classifier: Framework :: Django :: 2.1
Classifier: Intended Audience :: Developers
Classifier: License :: OSI Approved :: BSD License
Classifier: Natural Language :: English
Classifier: Programming Language :: Python :: 2
Classifier: Programming Language :: Python :: 2.7
Classifier: Programming Language :: Python :: 3
Classifier: Programming Language :: Python :: 3.2
Classifier: Programming Language :: Python :: 3.3
Classifier: Programming Language :: Python :: 3.4
Classifier: Programming Language :: Python :: 3.5
Requires-Dist: requests (==2.21.0)
Requires-Dist: iso8601 (==0.1.12)
Requires-Dist: six (==1.12.0)
Requires-Dist: django (>=1.11.20)
